mailsafeguard/__init__.py
mailsafeguard/core.py
tests/__init__.py
tests/test_core.py
mailsafeguard-0.3.0.dist-info/LICENSE
mailsafeguard-0.3.0.dist-info/METADATA
mailsafeguard-0.3.0.dist-info/WHEEL
mailsafeguard-0.3.0.dist-info/top_level.txt
mailsafeguard-0.3.0.dist-info/RECORD
