Metadata-Version: 2.1
Name: mailsafeguard
Version: 0.3.0
Summary: A robust Python package for validating and filtering disposable email addresses to enhance email integrity and security.
Home-page: https://github.com/thowfickofficial/mailsafeguard
Author: thowfickofficial
Project-URL: LinkedIn, https://www.linkedin.com/in/thowfickofficial/
Project-URL: Website, https://thowfickofficial.netlify.app/
Keywords: email validation,disposable email,email filtering,email security,Python package,email verification,spam prevention,email integrity,DNS resolution,email address validation,email protection,cybersecurity,email checker,email legitimacy,email hygiene,domain validation,email domain check,email format,email quality,email verification API,email address checker,email list management,email validation tool,email address validation tool,email blacklist,email whitelist,domain verification,DNS look
Classifier: Programming Language :: Python :: 3
Classifier: Operating System :: OS Independent
Classifier: Development Status :: 4 - Beta
Classifier: Intended Audience :: Developers
Classifier: Topic :: Software Development :: Libraries :: Python Modules
Classifier: Topic :: Internet :: WWW/HTTP :: Dynamic Content
Requires-Python: >=3.6
License-File: LICENSE
Requires-Dist: requests
Requires-Dist: dnspython
